{
    "id" : "2",
    "name" : "Ve dau mai toc nguoi thuong ",
    "singer" : "Quang Le",
    "artist" : "No name",
    "tone" : "Fm",
    "type" : "Nhac Tru tinh",
    "lyricssub" : "Hồn lỡ sa vào đôi mắt [Fm] em<br>Chiều nao xõa [C7] tóc ngồi bên [Fm] rèm<br>Thầm ước nhưng [Eb] nào đâu dám [C#] nói<br>Khép [Fm] tâm tư lại [Bbm] thôi<br>Đường hoa vẫn chưa mở [C7] lối<br>",
    "lyrics" : "1. Hồn lỡ sa vào đôi mắt [Fm] em<br>Chiều nao xõa [C7] tóc ngồi bên [Fm] rèm<br>Thầm ước nhưng [Eb] nào đâu dám [C#] nói<br>Khép [Fm] tâm tư lại [Bbm] thôi<br>Đường hoa vẫn chưa mở [C7] lối<br><br>2. Đời lắm phong trần tay trắng [Fm] tay<br>Trời đông ngại [C7] gió lùa vai [Fm] gầy<br>Lầu kín trăng [Eb] về không lối [C#] chiếu<br>Gác [Fm] cao ngăn niềm [Bbm] yêu<br>Thì [C7] thôi mơ ước chi [Fm] nhiều<br><br>ĐK:<br>Bên [Fm] nhau sao tình xa vạn [C#] lý<br>Cách [F7] biệt mấy sơn [Bbm] khê<br>Ngày [Eb] đi mắt em xanh biển [Bbm] sâu<br>Mắt [Eb] tôi rưng rưng [Ab] sầu<br>Lặng nghe tiếng [C7] pháo tiễn ai qua [Fm] cầu<br><br>3. Đường phố muôn màu sao thiếu [Fm] em<br>Về đâu làn [C7] tóc xõa bên [Fm] rèm<br>Lầu vắng không [Eb] người song khép [C#] kín<br>Nhớ [Fm] em tôi gọi [Bbm] tên<br>Chỉ [C7] nghe lá rơi [Fm] thềm",
    "beat" : "Bolero",
    "nhip" : "3/4"
  }